MANIFEST.in
README.rst
setup.py
sphinx_osgeocn_theme.py
sphinx_osgeocn_theme.egg-info/PKG-INFO
sphinx_osgeocn_theme.egg-info/SOURCES.txt
sphinx_osgeocn_theme.egg-info/dependency_links.txt
sphinx_osgeocn_theme.egg-info/top_level.txt
themes/sphinx-osgeocn-theme/breadcrumb.html
themes/sphinx-osgeocn-theme/footer.html
themes/sphinx-osgeocn-theme/globaltoc.html
themes/sphinx-osgeocn-theme/layout.html
themes/sphinx-osgeocn-theme/navbar.html
themes/sphinx-osgeocn-theme/navbarsearch.html
themes/sphinx-osgeocn-theme/search.html
themes/sphinx-osgeocn-theme/searchbox.html
themes/sphinx-osgeocn-theme/sourcelink.html
themes/sphinx-osgeocn-theme/theme.conf
themes/sphinx-osgeocn-theme/static/sphinxbootstrap4.css_t
themes/sphinx-osgeocn-theme/static/sphinxbootstrap4.js_t
themes/sphinx-osgeocn-theme/static/bootstrap-4.4.1-dist/css/bootstrap-grid.css
themes/sphinx-osgeocn-theme/static/bootstrap-4.4.1-dist/css/bootstrap-grid.css.map
themes/sphinx-osgeocn-theme/static/bootstrap-4.4.1-dist/css/bootstrap-grid.min.css
themes/sphinx-osgeocn-theme/static/bootstrap-4.4.1-dist/css/bootstrap-grid.min.css.map
themes/sphinx-osgeocn-theme/static/bootstrap-4.4.1-dist/css/bootstrap-reboot.css
themes/sphinx-osgeocn-theme/static/bootstrap-4.4.1-dist/css/bootstrap-reboot.css.map
themes/sphinx-osgeocn-theme/static/bootstrap-4.4.1-dist/css/bootstrap-reboot.min.css
themes/sphinx-osgeocn-theme/static/bootstrap-4.4.1-dist/css/bootstrap-reboot.min.css.map
themes/sphinx-osgeocn-theme/static/bootstrap-4.4.1-dist/css/bootstrap.css
themes/sphinx-osgeocn-theme/static/bootstrap-4.4.1-dist/css/bootstrap.css.map
themes/sphinx-osgeocn-theme/static/bootstrap-4.4.1-dist/css/bootstrap.min.css
themes/sphinx-osgeocn-theme/static/bootstrap-4.4.1-dist/css/bootstrap.min.css.map
themes/sphinx-osgeocn-theme/static/bootstrap-4.4.1-dist/js/bootstrap.bundle.js
themes/sphinx-osgeocn-theme/static/bootstrap-4.4.1-dist/js/bootstrap.bundle.js.map
themes/sphinx-osgeocn-theme/static/bootstrap-4.4.1-dist/js/bootstrap.bundle.min.js
themes/sphinx-osgeocn-theme/static/bootstrap-4.4.1-dist/js/bootstrap.bundle.min.js.map
themes/sphinx-osgeocn-theme/static/bootstrap-4.4.1-dist/js/bootstrap.js
