Metadata-Version: 1.1
Name: sphinx-osgeocn-theme
Version: 0.1.4
Summary: Sphinx Bootstrap4 Theme of OSGeo China Chapter Documents
Home-page: https://github.com/osgeocn/sphinx-osgeocn-theme
Author: OSGeo CN
Author-email: 486936@qq.com
License: MIT License
Platform: UNKNOWN
Classifier: Development Status :: 5 - Production/Stable
Classifier: Environment :: Web Environment
Classifier: Intended Audience :: Developers
Classifier: Intended Audience :: System Administrators
Classifier: License :: OSI Approved :: MIT License
Classifier: Operating System :: OS Independent
Classifier: Programming Language :: Python :: 3
Classifier: Topic :: Internet
Classifier: Topic :: Software Development :: Documentation
